danspeech/DanSpeechRecognizer.py
danspeech/Recognizer.py
danspeech/__init__.py
danspeech/audio/__init__.py
danspeech/audio/parsers.py
danspeech/audio/resources.py
danspeech/deepspeech/__init__.py
danspeech/deepspeech/decoder.py
danspeech/deepspeech/labels.json
danspeech/deepspeech/model.py
danspeech/deepspeech/utils.py
danspeech/errors/__init__.py
danspeech/errors/model_errors.py
danspeech/errors/recognizer_errors.py
danspeech/errors/training_errors.py
danspeech/language_models/__init__.py
danspeech/language_models/custom_lm.py
danspeech/language_models/dsl_3gram.py
danspeech/language_models/dsl_3gram_names.py
danspeech/language_models/dsl_5gram.py
danspeech/language_models/dsl_wiki_3gram.py
danspeech/language_models/dsl_wiki_5gram.py
danspeech/language_models/dsl_wiki_leipzig_3gram.py
danspeech/language_models/folketinget_3gram.py
danspeech/language_models/wiki_3gram.py
danspeech/language_models/wiki_5gram.py
danspeech/pretrained_models/__init__.py
danspeech/pretrained_models/baseline_model.py
danspeech/pretrained_models/custom_model.py
danspeech/pretrained_models/danspeech_primary.py
danspeech/pretrained_models/folketinget_model.py
danspeech/pretrained_models/librispeech.py
danspeech/pretrained_models/streaming_model_CPU.py
danspeech/pretrained_models/streaming_model_GPU.py
danspeech/pretrained_models/test_model.py
danspeech/pretrained_models/transfer_learned_model.py
danspeech/utils/__init__.py
danspeech/utils/data_utils.py
danspeech-1.0.4.dist-info/LICENSE.txt
danspeech-1.0.4.dist-info/METADATA
danspeech-1.0.4.dist-info/WHEEL
danspeech-1.0.4.dist-info/top_level.txt
danspeech-1.0.4.dist-info/RECORD
