Metadata-Version: 2.1
Name: danspeech
Version: 1.0.4
Summary: Speech recognition for Danish
Home-page: https://github.com/danspeech/danspeech
Author: Rasmus Arpe Fogh Jensen, Martin Carsten Nielsen
Author-email: rasmus.arpe@gmail.com, mcnielsen4270@gmail.com,
License: UNKNOWN
Platform: UNKNOWN
Classifier: Programming Language :: Python :: 3
Classifier: Development Status :: 5 - Production/Stable
Classifier: Operating System :: OS Independent
Requires-Dist: numpy
Requires-Dist: scipy
Requires-Dist: python-Levenshtein
Requires-Dist: wget
Requires-Dist: torch
Requires-Dist: six
Requires-Dist: librosa
